cimhub/CIMAdapter.py
cimhub/CIMHubConfig.py
cimhub/ClearDB.py
cimhub/CombineModelXMLFiles.py
cimhub/Compare_Cases.py
cimhub/ConvertModels.py
cimhub/CountClasses.py
cimhub/CreateHouses.py
cimhub/DropCircuit.py
cimhub/DropDER.py
cimhub/DropHouses.py
cimhub/DropMeasurements.py
cimhub/DropProfiles.py
cimhub/InsertDER.py
cimhub/InsertHouses.py
cimhub/InsertMeasurements.py
cimhub/InsertProfiles.py
cimhub/LineConstants.py
cimhub/ListFeeders.py
cimhub/ListMeasureables.py
cimhub/MakeConversionScript.py
cimhub/MakeGlmTestScript.py
cimhub/MakeLoopScript.py
cimhub/MakeTable.py
cimhub/SPARQL_Dict.py
cimhub/SummarizeDB.py
cimhub/__init__.py
cimhub/api.py
cimhub/constants_deprecated.py
cimhub/eia_recs/__init__.py
cimhub/eia_recs/housingData.py
cimhub/eia_recs/housing_data.json
cimhub-1.1.0.dist-info/METADATA
cimhub-1.1.0.dist-info/WHEEL
cimhub-1.1.0.dist-info/license.md
cimhub-1.1.0.dist-info/top_level.txt
cimhub-1.1.0.dist-info/RECORD
