Metadata-Version: 2.1
Name: cimhub
Version: 1.1.0
Summary: cimhub: Convert and validate electric power distribution system models.
Home-page: https://github.com/GRIDAPPSD/CIMHub
Author: Tom McDermott
Author-email: Thomas.McDermott@PNNL.gov
License: BSD
Project-URL: Bug Tracker, https://github.com/GRIDAPPSD/CIMHub/issues
Classifier: License :: OSI Approved :: BSD License
Classifier: Operating System :: OS Independent
Classifier: Programming Language :: Python :: 3.8
Classifier: Development Status :: 4 - Beta
Classifier: Environment :: Console
Classifier: Intended Audience :: Developers
Classifier: Intended Audience :: Education
Classifier: Intended Audience :: Science/Research
Classifier: Topic :: Scientific/Engineering
License-File: license.md
Requires-Dist: SPARQLWrapper (>=2.0.0)
Requires-Dist: numpy (>=1.23.0)
Requires-Dist: pandas (>=1.4.3)
Requires-Dist: lxml (>=4.9.0)
Requires-Dist: scipy (>=1.8.1)
